nonebot_plugin_uptime_kuma_puller/__init__.py
nonebot_plugin_uptime_kuma_puller/config.py
nonebot_plugin_uptime_kuma_puller-0.2.4.dist-info/licenses/LICENSE
nonebot_plugin_uptime_kuma_puller-0.2.4.dist-info/METADATA
nonebot_plugin_uptime_kuma_puller-0.2.4.dist-info/WHEEL
nonebot_plugin_uptime_kuma_puller-0.2.4.dist-info/top_level.txt
nonebot_plugin_uptime_kuma_puller-0.2.4.dist-info/RECORD
