Metadata-Version: 2.4
Name: nonebot_plugin_uptime_kuma_puller
Version: 0.2.4
Summary: This is a plugin that can generate a UptimeKuma status page summary for your Nonebot
Author-email: HTony03 <HTony03@foxmail.com>, bananaxiao2333 <banana.xiao@qq.com>
License-Expression: MIT
Project-URL: homepage, https://github.com/bananaxiao2333/nonebot-plugin-uptime-kuma-puller
Project-URL: repository, https://github.com/bananaxiao2333/nonebot-plugin-uptime-kuma-puller
Project-URL: changelog, https://github.com/bananaxiao2333/nonebot-plugin-uptime-kuma-puller/releases
Project-URL: issue, https://github.com/bananaxiao2333/nonebot-plugin-uptime-kuma-puller/issues
Keywords: nonebot,uptimekuma,qqbot
Classifier: Development Status :: 3 - Alpha
Classifier: Environment :: Plugins
Classifier: Operating System :: OS Independent
Classifier: Programming Language :: Python :: 3.9
Classifier: Programming Language :: Python :: 3.10
Classifier: Programming Language :: Python :: 3.11
Classifier: Topic :: Software Development :: Libraries :: Python Modules
License-File: LICENSE
Requires-Dist: aiohttp~=3.11
Requires-Dist: nonebot2~=2.3
Requires-Dist: nonebot-plugin-waiter~=0.8.1
Requires-Dist: nonebot-plugin-alconna~=0.57.6
Requires-Dist: nonebot-plugin-group-config~=0.2.5
Dynamic: license-file
